WeiXueyuanTkinterJiaochengFix1/README.md
WeiXueyuanTkinterJiaochengFix1/__init__.py
WeiXueyuanTkinterJiaochengFix1/__main__.py
WeiXueyuanTkinterJiaochengFix1/file.epub
WeiXueyuanTkinterJiaochengFix1/index.html
WeiXueyuanTkinterJiaochengFix1/css/__init__.py
WeiXueyuanTkinterJiaochengFix1/css/annotations.css
WeiXueyuanTkinterJiaochengFix1/css/main.css
WeiXueyuanTkinterJiaochengFix1/css/normalize.css
WeiXueyuanTkinterJiaochengFix1/css/popup.css
WeiXueyuanTkinterJiaochengFix1/font/__init__.py
WeiXueyuanTkinterJiaochengFix1/font/fontello.eot
WeiXueyuanTkinterJiaochengFix1/font/fontello.svg
WeiXueyuanTkinterJiaochengFix1/font/fontello.ttf
WeiXueyuanTkinterJiaochengFix1/font/fontello.woff
WeiXueyuanTkinterJiaochengFix1/img/__init__.py
WeiXueyuanTkinterJiaochengFix1/img/annotator-glyph-sprite.png
WeiXueyuanTkinterJiaochengFix1/img/annotator-icon-sprite.png
WeiXueyuanTkinterJiaochengFix1/img/apple-touch-icon.png
WeiXueyuanTkinterJiaochengFix1/img/cancelfullscreen.png
WeiXueyuanTkinterJiaochengFix1/img/close.png
WeiXueyuanTkinterJiaochengFix1/img/fullscreen.png
WeiXueyuanTkinterJiaochengFix1/img/loader.gif
WeiXueyuanTkinterJiaochengFix1/img/menu-icon.png
WeiXueyuanTkinterJiaochengFix1/img/save.png
WeiXueyuanTkinterJiaochengFix1/img/saved.png
WeiXueyuanTkinterJiaochengFix1/img/settings-s.png
WeiXueyuanTkinterJiaochengFix1/img/settings.png
WeiXueyuanTkinterJiaochengFix1/img/star.png
WeiXueyuanTkinterJiaochengFix1/js/__init__.py
WeiXueyuanTkinterJiaochengFix1/js/epub.js
WeiXueyuanTkinterJiaochengFix1/js/epub.min.js
WeiXueyuanTkinterJiaochengFix1/js/epub.min.map
WeiXueyuanTkinterJiaochengFix1/js/hooks.min.js
WeiXueyuanTkinterJiaochengFix1/js/hooks.min.map
WeiXueyuanTkinterJiaochengFix1/js/reader.js
WeiXueyuanTkinterJiaochengFix1/js/reader.js.map
WeiXueyuanTkinterJiaochengFix1/js/reader.min.js
WeiXueyuanTkinterJiaochengFix1/js/reader.min.map
WeiXueyuanTkinterJiaochengFix1/js/hooks/__init__.py
WeiXueyuanTkinterJiaochengFix1/js/hooks/extensions/__init__.py
wei_xueyuan_tkinter_jiaocheng_fix1-2025.3.25.1.dist-info/METADATA
wei_xueyuan_tkinter_jiaocheng_fix1-2025.3.25.1.dist-info/WHEEL
wei_xueyuan_tkinter_jiaocheng_fix1-2025.3.25.1.dist-info/entry_points.txt
wei_xueyuan_tkinter_jiaocheng_fix1-2025.3.25.1.dist-info/top_level.txt
wei_xueyuan_tkinter_jiaocheng_fix1-2025.3.25.1.dist-info/RECORD
